{
  "version": "4.0.0-beta.2",
  "flags": {},
  "shapes": [
    {
      "label": "crop_line",
      "score": null,
      "points": [
        [
          459.79283554252595,
          589.9121869276315
        ],
        [
          461.19378120427206,
          341.51146211254263
        ]
      ],
      "group_id": null,
      "description": "",
      "difficult": false,
      "shape_type": "linestrip",
      "flags": {},
      "attributes": {},
      "kie_linking": []
    },
    {
      "label": "crop_line",
      "score": null,
      "points": [
        [
          768.9402525480381,
          716.9360590985883
        ],
        [
          615.8962372532218,
          273.51928367644734
        ]
      ],
      "group_id": null,
      "description": "",
      "difficult": false,
      "shape_type": "linestrip",
      "flags": {},
      "attributes": {},
      "kie_linking": []
    },
    {
      "label": "crop_line",
      "score": null,
      "points": [
        [
          935.5975469958639,
          514.3873949327867
        ],
        [
          745.3993310182653,
          191.32874450137996
        ]
      ],
      "group_id": null,
      "description": "",
      "difficult": false,
      "shape_type": "linestrip",
      "flags": {},
      "attributes": {},
      "kie_linking": []
    },
    {
      "label": "crop_line",
      "score": null,
      "points": [
        [
          1298.9452894070243,
          609.1642234688289
        ],
        [
          920.9440991480129,
          132.4435695208761
        ]
      ],
      "group_id": null,
      "description": "",
      "difficult": false,
      "shape_type": "linestrip",
      "flags": {},
      "attributes": {},
      "kie_linking": []
    }
  ],
  "imagePath": "1310_rot3.jpg",
  "imageData": null,
  "imageHeight": 1114,
  "imageWidth": 1449
}