{
  "version": "4.0.0-beta.2",
  "flags": {},
  "shapes": [
    {
      "label": "crop_line",
      "score": null,
      "points": [
        [
          366.24892191303786,
          816.7633599811693
        ],
        [
          432.4421219956708,
          324.43278555086266
        ]
      ],
      "group_id": null,
      "description": "",
      "difficult": false,
      "shape_type": "linestrip",
      "flags": {},
      "attributes": {},
      "kie_linking": []
    },
    {
      "label": "crop_line",
      "score": null,
      "points": [
        [
          655.4889165120303,
          696.464925188159
        ],
        [
          584.4051546181947,
          283.31180193378555
        ]
      ],
      "group_id": null,
      "description": "",
      "difficult": false,
      "shape_type": "linestrip",
      "flags": {},
      "attributes": {},
      "kie_linking": []
    },
    {
      "label": "crop_line",
      "score": null,
      "points": [
        [
          959.954190682639,
          624.8771419881377
        ],
        [
          808.0237808583196,
          322.1107677521603
        ],
        [
          731.737472464902,
          218.0021344257347
        ]
      ],
      "group_id": null,
      "description": "",
      "difficult": false,
      "shape_type": "linestrip",
      "flags": {},
      "attributes": {},
      "kie_linking": []
    },
    {
      "label": "crop_line",
      "score": null,
      "points": [
        [
          1268.4459379852665,
          573.5247224851646
        ],
        [
          999.9725377078083,
          218.86116442196806
        ]
      ],
      "group_id": null,
      "description": "",
      "difficult": false,
      "shape_type": "linestrip",
      "flags": {},
      "attributes": {},
      "kie_linking": []
    }
  ],
  "imagePath": "1375_rot2.jpg",
  "imageData": null,
  "imageHeight": 1114,
  "imageWidth": 1449
}