{
  "version": "4.0.0-beta.2",
  "flags": {},
  "shapes": [
    {
      "label": "crop_line",
      "score": null,
      "points": [
        [
          355.55059931392634,
          551.3358086312795
        ],
        [
          462.27394326399764,
          70.8775666010308
        ]
      ],
      "group_id": null,
      "description": "",
      "difficult": false,
      "shape_type": "linestrip",
      "flags": {},
      "attributes": {},
      "kie_linking": []
    },
    {
      "label": "crop_line",
      "score": null,
      "points": [
        [
          700.8785427643498,
          370.7246298483108
        ],
        [
          624.0733616079124,
          42.629167152917134
        ]
      ],
      "group_id": null,
      "description": "",
      "difficult": false,
      "shape_type": "linestrip",
      "flags": {},
      "attributes": {},
      "kie_linking": []
    },
    {
      "label": "crop_line",
      "score": null,
      "points": [
        [
          895.6831411841481,
          486.5083580945888
        ],
        [
          830.0848617557799,
          113.47356466062651
        ]
      ],
      "group_id": null,
      "description": "",
      "difficult": false,
      "shape_type": "linestrip",
      "flags": {},
      "attributes": {},
      "kie_linking": []
    },
    {
      "label": "crop_line",
      "score": null,
      "points": [
        [
          1209.2230902985543,
          435.9507912139545
        ],
        [
          930.7291743514714,
          37.419505655290756
        ]
      ],
      "group_id": null,
      "description": "",
      "difficult": false,
      "shape_type": "linestrip",
      "flags": {},
      "attributes": {},
      "kie_linking": []
    }
  ],
  "imagePath": "1505_persp.jpg",
  "imageData": null,
  "imageHeight": 791,
  "imageWidth": 1275
}