{
  "version": "4.0.0-beta.2",
  "flags": {},
  "shapes": [
    {
      "label": "crop_line",
      "score": null,
      "points": [
        [
          372.9681992341992,
          457.58091463018314
        ],
        [
          519.7111480377527,
          25.82971424226789
        ]
      ],
      "group_id": null,
      "description": "",
      "difficult": false,
      "shape_type": "linestrip",
      "flags": {},
      "attributes": {},
      "kie_linking": []
    },
    {
      "label": "crop_line",
      "score": null,
      "points": [
        [
          637.7313949289978,
          532.017284337192
        ],
        [
          643.4617959933319,
          90.64420588212609
        ]
      ],
      "group_id": null,
      "description": "",
      "difficult": false,
      "shape_type": "linestrip",
      "flags": {},
      "attributes": {},
      "kie_linking": []
    },
    {
      "label": "crop_line",
      "score": null,
      "points": [
        [
          972.2468395975129,
          607.568542570336
        ],
        [
          855.3867696484115,
          39.688813062363934
        ]
      ],
      "group_id": null,
      "description": "",
      "difficult": false,
      "shape_type": "linestrip",
      "flags": {},
      "attributes": {},
      "kie_linking": []
    },
    {
      "label": "crop_line",
      "score": null,
      "points": [
        [
          1203.011961483546,
          373.41131888565695
        ],
        [
          1036.9456452679847,
          38.92253989378284
        ]
      ],
      "group_id": null,
      "description": "",
      "difficult": false,
      "shape_type": "linestrip",
      "flags": {},
      "attributes": {},
      "kie_linking": []
    }
  ],
  "imagePath": "680_persp.jpg",
  "imageData": null,
  "imageHeight": 704,
  "imageWidth": 1326
}