{
  "version": "4.0.0-beta.2",
  "flags": {},
  "shapes": [
    {
      "label": "crop_line",
      "score": null,
      "points": [
        [
          942.1372549019608,
          475.2941176470589
        ],
        [
          807.2352941176471,
          29.80392156862743
        ]
      ],
      "group_id": null,
      "description": "",
      "difficult": false,
      "shape_type": "linestrip",
      "flags": {},
      "attributes": {},
      "kie_linking": []
    },
    {
      "label": "crop_line",
      "score": null,
      "points": [
        [
          678.6078431372549,
          511.37254901960773
        ],
        [
          651.156862745098,
          36.078431372549005
        ]
      ],
      "group_id": null,
      "description": "",
      "difficult": false,
      "shape_type": "linestrip",
      "flags": {},
      "attributes": {},
      "kie_linking": []
    },
    {
      "label": "crop_line",
      "score": null,
      "points": [
        [
          273.1176470588234,
          632.156862745098
        ],
        [
          386.0588235294117,
          334.11764705882354
        ],
        [
          438.6078431372549,
          150.5882352941176
        ]
      ],
      "group_id": null,
      "description": "",
      "difficult": false,
      "shape_type": "linestrip",
      "flags": {},
      "attributes": {},
      "kie_linking": []
    },
    {
      "label": "crop_line",
      "score": null,
      "points": [
        [
          44.88235294117635,
          416.47058823529414
        ],
        [
          243.31372549019602,
          42.35294117647058
        ]
      ],
      "group_id": null,
      "description": "",
      "difficult": false,
      "shape_type": "linestrip",
      "flags": {},
      "attributes": {},
      "kie_linking": []
    }
  ],
  "imagePath": "725_flip.jpg",
  "imageData": null,
  "imageHeight": 720,
  "imageWidth": 1280
}