{
  "version": "4.0.0-beta.2",
  "flags": {},
  "shapes": [
    {
      "label": "crop_line",
      "score": null,
      "points": [
        [
          963.8863461968024,
          903.3852246662925
        ],
        [
          963.3242226215506,
          360.0191023872019
        ]
      ],
      "group_id": null,
      "description": "",
      "difficult": false,
      "shape_type": "linestrip",
      "flags": {},
      "attributes": {},
      "kie_linking": []
    },
    {
      "label": "crop_line",
      "score": null,
      "points": [
        [
          671.9582847330565,
          659.5191474834853
        ],
        [
          795.5280479591853,
          201.38086837777266
        ]
      ],
      "group_id": null,
      "description": "",
      "difficult": false,
      "shape_type": "linestrip",
      "flags": {},
      "attributes": {},
      "kie_linking": []
    },
    {
      "label": "crop_line",
      "score": null,
      "points": [
        [
          473.70318783452217,
          411.52133806168297
        ],
        [
          608.2258420555426,
          173.1168891504784
        ]
      ],
      "group_id": null,
      "description": "",
      "difficult": false,
      "shape_type": "linestrip",
      "flags": {},
      "attributes": {},
      "kie_linking": []
    },
    {
      "label": "crop_line",
      "score": null,
      "points": [
        [
          160.1516953810169,
          378.6602919052206
        ],
        [
          453.35526044276526,
          105.63603970099837
        ]
      ],
      "group_id": null,
      "description": "",
      "difficult": false,
      "shape_type": "linestrip",
      "flags": {},
      "attributes": {},
      "kie_linking": []
    }
  ],
  "imagePath": "795_rot_flip.jpg",
  "imageData": null,
  "imageHeight": 1026,
  "imageWidth": 1422
}