{
  "version": "4.0.0-beta.2",
  "flags": {},
  "shapes": [
    {
      "label": "crop_line",
      "score": null,
      "points": [
        [
          264.13826603383336,
          561.9934830475825
        ],
        [
          514.5121463090117,
          140.23953148071948
        ]
      ],
      "group_id": null,
      "description": "",
      "difficult": false,
      "shape_type": "linestrip",
      "flags": {},
      "attributes": {},
      "kie_linking": []
    },
    {
      "label": "crop_line",
      "score": null,
      "points": [
        [
          531.8824081701517,
          570.1797608152874
        ],
        [
          686.5255623105649,
          140.30644266628266
        ]
      ],
      "group_id": null,
      "description": "",
      "difficult": false,
      "shape_type": "linestrip",
      "flags": {},
      "attributes": {},
      "kie_linking": []
    },
    {
      "label": "crop_line",
      "score": null,
      "points": [
        [
          812.4604172419911,
          406.2145422548783
        ],
        [
          839.2327937255237,
          164.04719559831125
        ]
      ],
      "group_id": null,
      "description": "",
      "difficult": false,
      "shape_type": "linestrip",
      "flags": {},
      "attributes": {},
      "kie_linking": []
    },
    {
      "label": "crop_line",
      "score": null,
      "points": [
        [
          1202.4640444600823,
          714.7030260155227
        ],
        [
          1030.4218566967531,
          181.83072523790875
        ]
      ],
      "group_id": null,
      "description": "",
      "difficult": false,
      "shape_type": "linestrip",
      "flags": {},
      "attributes": {},
      "kie_linking": []
    }
  ],
  "imagePath": "905_rot1.jpg",
  "imageData": null,
  "imageHeight": 931,
  "imageWidth": 1385
}