{
  "version": "4.0.0-beta.2",
  "flags": {},
  "shapes": [
    {
      "label": "crop_line",
      "score": null,
      "points": [
        [
          481.0526315789474,
          927.1345029239765
        ],
        [
          879.8830409356724,
          38.245614035087755
        ]
      ],
      "group_id": null,
      "description": "",
      "difficult": false,
      "shape_type": "linestrip",
      "flags": {},
      "attributes": {},
      "kie_linking": []
    },
    {
      "label": "crop_line",
      "score": null,
      "points": [
        [
          1054.1520467836256,
          935.3216374269002
        ],
        [
          973.4502923976607,
          69.8245614035088
        ]
      ],
      "group_id": null,
      "description": "",
      "difficult": false,
      "shape_type": "linestrip",
      "flags": {},
      "attributes": {},
      "kie_linking": []
    },
    {
      "label": "crop_line",
      "score": null,
      "points": [
        [
          1637.7777777777776,
          1025.380116959064
        ],
        [
          1076.3742690058477,
          46.43274853801171
        ]
      ],
      "group_id": null,
      "description": "",
      "difficult": false,
      "shape_type": "linestrip",
      "flags": {},
      "attributes": {},
      "kie_linking": []
    }
  ],
  "imagePath": "IMG_7449_frame_14.jpg",
  "imageData": null,
  "imageHeight": 1080,
  "imageWidth": 1920
}