{
  "version": "4.0.0-beta.2",
  "flags": {},
  "shapes": [
    {
      "label": "crop_line",
      "score": null,
      "points": [
        [
          504.0288939735371,
          1035.4777880564611
        ],
        [
          1182.824791769447,
          336.60349223980927
        ]
      ],
      "group_id": null,
      "description": "",
      "difficult": false,
      "shape_type": "linestrip",
      "flags": {},
      "attributes": {},
      "kie_linking": []
    },
    {
      "label": "crop_line",
      "score": null,
      "points": [
        [
          1039.766020501976,
          1239.1827220624014
        ],
        [
          1259.9486114104757,
          398.2798808097192
        ]
      ],
      "group_id": null,
      "description": "",
      "difficult": false,
      "shape_type": "linestrip",
      "flags": {},
      "attributes": {},
      "kie_linking": []
    },
    {
      "label": "crop_line",
      "score": null,
      "points": [
        [
          1557.3929991406799,
          1523.4217668811425
        ],
        [
          1364.6659839200352,
          411.5008401043866
        ]
      ],
      "group_id": null,
      "description": "",
      "difficult": false,
      "shape_type": "linestrip",
      "flags": {},
      "attributes": {},
      "kie_linking": []
    }
  ],
  "imagePath": "IMG_7449_frame_14_rot1.jpg",
  "imageData": null,
  "imageHeight": 1671,
  "imageWidth": 2173
}