{
  "version": "4.0.0-beta.2",
  "flags": {},
  "shapes": [
    {
      "label": "crop_line",
      "score": null,
      "points": [
        [
          475.2046783625731,
          863.9766081871342
        ],
        [
          821.4035087719299,
          42.92397660818713
        ]
      ],
      "group_id": null,
      "description": "",
      "difficult": false,
      "shape_type": "linestrip",
      "flags": {},
      "attributes": {},
      "kie_linking": []
    },
    {
      "label": "crop_line",
      "score": null,
      "points": [
        [
          1001.5204678362572,
          804.3274853801167
        ],
        [
          898.5964912280701,
          42.92397660818713
        ]
      ],
      "group_id": null,
      "description": "",
      "difficult": false,
      "shape_type": "linestrip",
      "flags": {},
      "attributes": {},
      "kie_linking": []
    },
    {
      "label": "crop_line",
      "score": null,
      "points": [
        [
          1520.8187134502923,
          1000.8187134502923
        ],
        [
          981.6374269005846,
          32.39766081871346
        ]
      ],
      "group_id": null,
      "description": "",
      "difficult": false,
      "shape_type": "linestrip",
      "flags": {},
      "attributes": {},
      "kie_linking": []
    }
  ],
  "imagePath": "IMG_7449_frame_29.jpg",
  "imageData": null,
  "imageHeight": 1080,
  "imageWidth": 1920
}