{
  "version": "4.0.0-beta.2",
  "flags": {},
  "shapes": [
    {
      "label": "crop_line",
      "score": null,
      "points": [
        [
          1565.2961716456884,
          1227.0827781044743
        ],
        [
          1389.6730029711068,
          350.59289822404605
        ]
      ],
      "group_id": null,
      "description": "",
      "difficult": false,
      "shape_type": "linestrip",
      "flags": {},
      "attributes": {},
      "kie_linking": []
    },
    {
      "label": "crop_line",
      "score": null,
      "points": [
        [
          897.6746810193672,
          1129.3210442069576
        ],
        [
          1217.1040968325028,
          321.3050898588663
        ]
      ],
      "group_id": null,
      "description": "",
      "difficult": false,
      "shape_type": "linestrip",
      "flags": {},
      "attributes": {},
      "kie_linking": []
    },
    {
      "label": "crop_line",
      "score": null,
      "points": [
        [
          147.13912875437313,
          1002.0774584492964
        ],
        [
          970.3997867253702,
          229.77303318631067
        ]
      ],
      "group_id": null,
      "description": "",
      "difficult": false,
      "shape_type": "linestrip",
      "flags": {},
      "attributes": {},
      "kie_linking": []
    },
    {
      "label": "crop_line",
      "score": null,
      "points": [
        [
          1798.219324525479,
          872.962177985466
        ],
        [
          1598.3717852148202,
          407.72441772142076
        ]
      ],
      "group_id": null,
      "description": "",
      "difficult": false,
      "shape_type": "linestrip",
      "flags": {},
      "attributes": {},
      "kie_linking": []
    },
    {
      "label": "crop_line",
      "score": null,
      "points": [
        [
          203.87829813062967,
          428.8078968297774
        ],
        [
          732.4089329852884,
          159.94932945159752
        ]
      ],
      "group_id": null,
      "description": "",
      "difficult": false,
      "shape_type": "linestrip",
      "flags": {},
      "attributes": {},
      "kie_linking": []
    }
  ],
  "imagePath": "IMG_7449_frame_81_rot_flip.jpg",
  "imageData": null,
  "imageHeight": 1540,
  "imageWidth": 2134
}