{
  "version": "4.0.0-beta.2",
  "flags": {},
  "shapes": [
    {
      "label": "meadow_grass",
      "score": null,
      "points": [
        [
          162.0,
          258.0
        ],
        [
          161.0,
          259.0
        ],
        [
          160.0,
          259.0
        ],
        [
          160.0,
          260.0
        ],
        [
          159.0,
          261.0
        ],
        [
          159.0,
          262.0
        ],
        [
          158.0,
          263.0
        ],
        [
          158.0,
          264.0
        ],
        [
          157.0,
          265.0
        ],
        [
          157.0,
          267.0
        ],
        [
          156.0,
          268.0
        ],
        [
          156.0,
          270.0
        ],
        [
          155.0,
          271.0
        ],
        [
          155.0,
          272.0
        ],
        [
          152.0,
          275.0
        ],
        [
          152.0,
          276.0
        ],
        [
          150.0,
          278.0
        ],
        [
          150.0,
          288.0
        ],
        [
          151.0,
          289.0
        ],
        [
          151.0,
          295.0
        ],
        [
          152.0,
          296.0
        ],
        [
          154.0,
          296.0
        ],
        [
          155.0,
          297.0
        ],
        [
          156.0,
          297.0
        ],
        [
          157.0,
          296.0
        ],
        [
          159.0,
          296.0
        ],
        [
          160.0,
          295.0
        ],
        [
          161.0,
          295.0
        ],
        [
          163.0,
          293.0
        ],
        [
          163.0,
          291.0
        ],
        [
          164.0,
          290.0
        ],
        [
          164.0,
          289.0
        ],
        [
          166.0,
          287.0
        ],
        [
          166.0,
          286.0
        ],
        [
          170.0,
          282.0
        ],
        [
          172.0,
          282.0
        ],
        [
          173.0,
          281.0
        ],
        [
          175.0,
          281.0
        ],
        [
          176.0,
          280.0
        ],
        [
          177.0,
          280.0
        ],
        [
          179.0,
          278.0
        ],
        [
          179.0,
          277.0
        ],
        [
          182.0,
          274.0
        ],
        [
          182.0,
          273.0
        ],
        [
          183.0,
          272.0
        ],
        [
          183.0,
          270.0
        ],
        [
          181.0,
          268.0
        ],
        [
          179.0,
          268.0
        ],
        [
          178.0,
          269.0
        ],
        [
          177.0,
          269.0
        ],
        [
          175.0,
          271.0
        ],
        [
          174.0,
          271.0
        ],
        [
          174.0,
          273.0
        ],
        [
          173.0,
          274.0
        ],
        [
          172.0,
          274.0
        ],
        [
          171.0,
          275.0
        ],
        [
          170.0,
          275.0
        ],
        [
          169.0,
          276.0
        ],
        [
          167.0,
          276.0
        ],
        [
          166.0,
          277.0
        ],
        [
          165.0,
          277.0
        ],
        [
          160.0,
          282.0
        ],
        [
          160.0,
          284.0
        ],
        [
          158.0,
          286.0
        ],
        [
          157.0,
          285.0
        ],
        [
          157.0,
          284.0
        ],
        [
          156.0,
          283.0
        ],
        [
          156.0,
          282.0
        ],
        [
          157.0,
          281.0
        ],
        [
          157.0,
          280.0
        ],
        [
          162.0,
          275.0
        ],
        [
          162.0,
          272.0
        ],
        [
          163.0,
          271.0
        ],
        [
          163.0,
          269.0
        ],
        [
          164.0,
          268.0
        ],
        [
          164.0,
          266.0
        ],
        [
          165.0,
          265.0
        ],
        [
          165.0,
          261.0
        ],
        [
          164.0,
          260.0
        ],
        [
          164.0,
          259.0
        ],
        [
          163.0,
          259.0
        ]
      ],
      "group_id": null,
      "description": "",
      "difficult": false,
      "shape_type": "polygon",
      "flags": {},
      "attributes": {},
      "kie_linking": []
    },
    {
      "label": "meadow_grass",
      "score": null,
      "points": [
        [
          299.0,
          307.0
        ],
        [
          298.0,
          308.0
        ],
        [
          298.0,
          309.0
        ],
        [
          297.0,
          310.0
        ],
        [
          297.0,
          311.0
        ],
        [
          298.0,
          312.0
        ],
        [
          298.0,
          313.0
        ],
        [
          299.0,
          314.0
        ],
        [
          301.0,
          314.0
        ],
        [
          302.0,
          315.0
        ],
        [
          303.0,
          315.0
        ],
        [
          304.0,
          316.0
        ],
        [
          305.0,
          316.0
        ],
        [
          306.0,
          317.0
        ],
        [
          308.0,
          317.0
        ],
        [
          309.0,
          318.0
        ],
        [
          310.0,
          318.0
        ],
        [
          311.0,
          319.0
        ],
        [
          312.0,
          319.0
        ],
        [
          314.0,
          321.0
        ],
        [
          316.0,
          321.0
        ],
        [
          317.0,
          322.0
        ],
        [
          320.0,
          322.0
        ],
        [
          321.0,
          323.0
        ],
        [
          322.0,
          323.0
        ],
        [
          325.0,
          326.0
        ],
        [
          326.0,
          326.0
        ],
        [
          328.0,
          328.0
        ],
        [
          329.0,
          328.0
        ],
        [
          330.0,
          329.0
        ],
        [
          332.0,
          329.0
        ],
        [
          336.0,
          333.0
        ],
        [
          341.0,
          333.0
        ],
        [
          343.0,
          331.0
        ],
        [
          343.0,
          329.0
        ],
        [
          342.0,
          328.0
        ],
        [
          342.0,
          327.0
        ],
        [
          341.0,
          327.0
        ],
        [
          340.0,
          326.0
        ],
        [
          339.0,
          326.0
        ],
        [
          337.0,
          324.0
        ],
        [
          336.0,
          324.0
        ],
        [
          335.0,
          323.0
        ],
        [
          333.0,
          323.0
        ],
        [
          332.0,
          322.0
        ],
        [
          332.0,
          321.0
        ],
        [
          331.0,
          321.0
        ],
        [
          330.0,
          320.0
        ],
        [
          329.0,
          320.0
        ],
        [
          327.0,
          318.0
        ],
        [
          326.0,
          318.0
        ],
        [
          325.0,
          317.0
        ],
        [
          324.0,
          317.0
        ],
        [
          323.0,
          316.0
        ],
        [
          321.0,
          316.0
        ],
        [
          320.0,
          315.0
        ],
        [
          318.0,
          315.0
        ],
        [
          316.0,
          313.0
        ],
        [
          314.0,
          313.0
        ],
        [
          313.0,
          312.0
        ],
        [
          312.0,
          312.0
        ],
        [
          311.0,
          311.0
        ],
        [
          310.0,
          311.0
        ],
        [
          309.0,
          310.0
        ],
        [
          308.0,
          310.0
        ],
        [
          307.0,
          309.0
        ],
        [
          305.0,
          309.0
        ],
        [
          304.0,
          308.0
        ],
        [
          303.0,
          308.0
        ],
        [
          302.0,
          307.0
        ]
      ],
      "group_id": null,
      "description": "",
      "difficult": false,
      "shape_type": "polygon",
      "flags": {},
      "attributes": {},
      "kie_linking": []
    },
    {
      "label": "meadow_grass",
      "score": null,
      "points": [
        [
          56.0,
          320.0
        ],
        [
          55.0,
          321.0
        ],
        [
          53.0,
          321.0
        ],
        [
          50.0,
          324.0
        ],
        [
          50.0,
          327.0
        ],
        [
          48.0,
          329.0
        ],
        [
          48.0,
          331.0
        ],
        [
          47.0,
          332.0
        ],
        [
          47.0,
          334.0
        ],
        [
          46.0,
          335.0
        ],
        [
          46.0,
          337.0
        ],
        [
          45.0,
          338.0
        ],
        [
          45.0,
          341.0
        ],
        [
          44.0,
          342.0
        ],
        [
          44.0,
          344.0
        ],
        [
          43.0,
          345.0
        ],
        [
          43.0,
          347.0
        ],
        [
          40.0,
          350.0
        ],
        [
          40.0,
          351.0
        ],
        [
          36.0,
          355.0
        ],
        [
          35.0,
          355.0
        ],
        [
          33.0,
          353.0
        ],
        [
          32.0,
          353.0
        ],
        [
          28.0,
          349.0
        ],
        [
          28.0,
          348.0
        ],
        [
          26.0,
          346.0
        ],
        [
          26.0,
          345.0
        ],
        [
          24.0,
          343.0
        ],
        [
          24.0,
          342.0
        ],
        [
          23.0,
          341.0
        ],
        [
          22.0,
          341.0
        ],
        [
          20.0,
          339.0
        ],
        [
          17.0,
          339.0
        ],
        [
          16.0,
          338.0
        ],
        [
          13.0,
          338.0
        ],
        [
          12.0,
          339.0
        ],
        [
          10.0,
          339.0
        ],
        [
          10.0,
          344.0
        ],
        [
          11.0,
          345.0
        ],
        [
          11.0,
          346.0
        ],
        [
          13.0,
          348.0
        ],
        [
          17.0,
          348.0
        ],
        [
          18.0,
          347.0
        ],
        [
          21.0,
          350.0
        ],
        [
          21.0,
          351.0
        ],
        [
          25.0,
          355.0
        ],
        [
          25.0,
          356.0
        ],
        [
          27.0,
          358.0
        ],
        [
          28.0,
          358.0
        ],
        [
          30.0,
          360.0
        ],
        [
          30.0,
          361.0
        ],
        [
          29.0,
          362.0
        ],
        [
          28.0,
          362.0
        ],
        [
          27.0,
          363.0
        ],
        [
          26.0,
          363.0
        ],
        [
          20.0,
          369.0
        ],
        [
          20.0,
          370.0
        ],
        [
          19.0,
          371.0
        ],
        [
          18.0,
          371.0
        ],
        [
          18.0,
          372.0
        ],
        [
          16.0,
          374.0
        ],
        [
          16.0,
          375.0
        ],
        [
          14.0,
          377.0
        ],
        [
          14.0,
          378.0
        ],
        [
          13.0,
          379.0
        ],
        [
          13.0,
          380.0
        ],
        [
          12.0,
          381.0
        ],
        [
          12.0,
          386.0
        ],
        [
          13.0,
          387.0
        ],
        [
          13.0,
          389.0
        ],
        [
          14.0,
          390.0
        ],
        [
          14.0,
          392.0
        ],
        [
          15.0,
          393.0
        ],
        [
          15.0,
          395.0
        ],
        [
          16.0,
          396.0
        ],
        [
          16.0,
          401.0
        ],
        [
          17.0,
          402.0
        ],
        [
          17.0,
          403.0
        ],
        [
          19.0,
          405.0
        ],
        [
          19.0,
          406.0
        ],
        [
          20.0,
          407.0
        ],
        [
          20.0,
          413.0
        ],
        [
          21.0,
          414.0
        ],
        [
          21.0,
          416.0
        ],
        [
          22.0,
          417.0
        ],
        [
          22.0,
          420.0
        ],
        [
          23.0,
          421.0
        ],
        [
          23.0,
          422.0
        ],
        [
          24.0,
          423.0
        ],
        [
          25.0,
          423.0
        ],
        [
          26.0,
          424.0
        ],
        [
          27.0,
          424.0
        ],
        [
          30.0,
          427.0
        ],
        [
          30.0,
          428.0
        ],
        [
          36.0,
          434.0
        ],
        [
          36.0,
          436.0
        ],
        [
          37.0,
          437.0
        ],
        [
          37.0,
          438.0
        ],
        [
          38.0,
          438.0
        ],
        [
          39.0,
          439.0
        ],
        [
          39.0,
          440.0
        ],
        [
          40.0,
          441.0
        ],
        [
          40.0,
          443.0
        ],
        [
          42.0,
          445.0
        ],
        [
          42.0,
          446.0
        ],
        [
          43.0,
          447.0
        ],
        [
          43.0,
          448.0
        ],
        [
          44.0,
          448.0
        ],
        [
          45.0,
          449.0
        ],
        [
          45.0,
          451.0
        ],
        [
          48.0,
          454.0
        ],
        [
          48.0,
          456.0
        ],
        [
          49.0,
          457.0
        ],
        [
          49.0,
          458.0
        ],
        [
          50.0,
          459.0
        ],
        [
          50.0,
          463.0
        ],
        [
          51.0,
          464.0
        ],
        [
          51.0,
          466.0
        ],
        [
          52.0,
          467.0
        ],
        [
          52.0,
          468.0
        ],
        [
          53.0,
          468.0
        ],
        [
          55.0,
          470.0
        ],
        [
          55.0,
          471.0
        ],
        [
          56.0,
          472.0
        ],
        [
          56.0,
          473.0
        ],
        [
          58.0,
          475.0
        ],
        [
          58.0,
          477.0
        ],
        [
          59.0,
          478.0
        ],
        [
          59.0,
          480.0
        ],
        [
          61.0,
          482.0
        ],
        [
          61.0,
          483.0
        ],
        [
          62.0,
          484.0
        ],
        [
          63.0,
          484.0
        ],
        [
          64.0,
          485.0
        ],
        [
          67.0,
          485.0
        ],
        [
          68.0,
          484.0
        ],
        [
          68.0,
          479.0
        ],
        [
          67.0,
          479.0
        ],
        [
          66.0,
          478.0
        ],
        [
          66.0,
          477.0
        ],
        [
          65.0,
          476.0
        ],
        [
          65.0,
          475.0
        ],
        [
          64.0,
          474.0
        ],
        [
          64.0,
          473.0
        ],
        [
          63.0,
          472.0
        ],
        [
          63.0,
          470.0
        ],
        [
          61.0,
          468.0
        ],
        [
          61.0,
          467.0
        ],
        [
          60.0,
          466.0
        ],
        [
          60.0,
          465.0
        ],
        [
          57.0,
          462.0
        ],
        [
          57.0,
          460.0
        ],
        [
          56.0,
          459.0
        ],
        [
          56.0,
          456.0
        ],
        [
          55.0,
          455.0
        ],
        [
          55.0,
          454.0
        ],
        [
          54.0,
          453.0
        ],
        [
          54.0,
          451.0
        ],
        [
          53.0,
          450.0
        ],
        [
          53.0,
          449.0
        ],
        [
          49.0,
          445.0
        ],
        [
          49.0,
          443.0
        ],
        [
          47.0,
          441.0
        ],
        [
          47.0,
          439.0
        ],
        [
          45.0,
          437.0
        ],
        [
          45.0,
          436.0
        ],
        [
          44.0,
          435.0
        ],
        [
          44.0,
          434.0
        ],
        [
          43.0,
          433.0
        ],
        [
          43.0,
          432.0
        ],
        [
          41.0,
          430.0
        ],
        [
          41.0,
          429.0
        ],
        [
          39.0,
          427.0
        ],
        [
          39.0,
          426.0
        ],
        [
          37.0,
          424.0
        ],
        [
          36.0,
          424.0
        ],
        [
          34.0,
          422.0
        ],
        [
          34.0,
          421.0
        ],
        [
          29.0,
          416.0
        ],
        [
          29.0,
          414.0
        ],
        [
          27.0,
          412.0
        ],
        [
          27.0,
          409.0
        ],
        [
          26.0,
          408.0
        ],
        [
          26.0,
          405.0
        ],
        [
          25.0,
          404.0
        ],
        [
          25.0,
          402.0
        ],
        [
          24.0,
          401.0
        ],
        [
          24.0,
          400.0
        ],
        [
          23.0,
          399.0
        ],
        [
          23.0,
          397.0
        ],
        [
          22.0,
          396.0
        ],
        [
          22.0,
          394.0
        ],
        [
          21.0,
          393.0
        ],
        [
          21.0,
          391.0
        ],
        [
          20.0,
          390.0
        ],
        [
          20.0,
          386.0
        ],
        [
          19.0,
          385.0
        ],
        [
          19.0,
          383.0
        ],
        [
          20.0,
          382.0
        ],
        [
          20.0,
          381.0
        ],
        [
          21.0,
          380.0
        ],
        [
          21.0,
          379.0
        ],
        [
          25.0,
          375.0
        ],
        [
          25.0,
          374.0
        ],
        [
          30.0,
          369.0
        ],
        [
          31.0,
          369.0
        ],
        [
          32.0,
          368.0
        ],
        [
          39.0,
          368.0
        ],
        [
          41.0,
          366.0
        ],
        [
          43.0,
          366.0
        ],
        [
          44.0,
          365.0
        ],
        [
          45.0,
          365.0
        ],
        [
          46.0,
          364.0
        ],
        [
          46.0,
          360.0
        ],
        [
          44.0,
          360.0
        ],
        [
          43.0,
          359.0
        ],
        [
          43.0,
          358.0
        ],
        [
          44.0,
          357.0
        ],
        [
          44.0,
          356.0
        ],
        [
          46.0,
          354.0
        ],
        [
          47.0,
          354.0
        ],
        [
          48.0,
          353.0
        ],
        [
          48.0,
          352.0
        ],
        [
          49.0,
          351.0
        ],
        [
          49.0,
          349.0
        ],
        [
          50.0,
          348.0
        ],
        [
          50.0,
          345.0
        ],
        [
          51.0,
          344.0
        ],
        [
          51.0,
          342.0
        ],
        [
          52.0,
          341.0
        ],
        [
          52.0,
          340.0
        ],
        [
          53.0,
          339.0
        ],
        [
          53.0,
          334.0
        ],
        [
          54.0,
          333.0
        ],
        [
          58.0,
          333.0
        ],
        [
          60.0,
          331.0
        ],
        [
          60.0,
          330.0
        ],
        [
          61.0,
          329.0
        ],
        [
          61.0,
          323.0
        ],
        [
          60.0,
          322.0
        ],
        [
          60.0,
          321.0
        ],
        [
          59.0,
          321.0
        ],
        [
          58.0,
          320.0
        ]
      ],
      "group_id": null,
      "description": "",
      "difficult": false,
      "shape_type": "polygon",
      "flags": {},
      "attributes": {},
      "kie_linking": []
    }
  ],
  "imagePath": "ave-0076-0002_crop01.jpg",
  "imageData": null,
  "imageHeight": 640,
  "imageWidth": 640
}